cached_notion/__init__.py
cached_notion/cached_api_endpoints.py
cached_notion/cached_client.py
cached_notion/models/__init__.py
cached_notion/models/base.py
cached_notion/models/property.py
cached_notion/notion_cache.sqlite
cached_notion/pretty_logger.py
cached_notion/utils.py
cached_notion-0.1.6.dist-info/WHEEL
cached_notion-0.1.6.dist-info/METADATA
cached_notion-0.1.6.dist-info/RECORD
