Metadata-Version: 2.1
Name: cached-notion
Version: 0.1.6
Summary: 
Author: tim-watcha
Author-email: tim@watcha.com
Requires-Python: >=3.9.1,<4.0.0
Classifier: Programming Language :: Python :: 3
Classifier: Programming Language :: Python :: 3.10
Classifier: Programming Language :: Python :: 3.11
Requires-Dist: coloredlogs (>=15.0.1,<16.0.0)
Requires-Dist: notion-client (>=2.0.0,<3.0.0)
Requires-Dist: pydantic (>=2.5.2,<3.0.0)
Requires-Dist: sqlitedict (>=2.1.0,<3.0.0)
Requires-Dist: tenacity (>=8.2.3,<9.0.0)
Requires-Dist: tqdm (>=4.66.1,<5.0.0)
